cellmaps_hierarchyeval/__init__.py
cellmaps_hierarchyeval/analysis.py
cellmaps_hierarchyeval/cellmaps_hierarchyevalcmd.py
cellmaps_hierarchyeval/default_prompt.txt
cellmaps_hierarchyeval/exceptions.py
cellmaps_hierarchyeval/perturb.py
cellmaps_hierarchyeval/readme_outputs.txt
cellmaps_hierarchyeval/runner.py
cellmaps_hierarchyeval-0.2.2.data/scripts/cellmaps_hierarchyevalcmd.py
cellmaps_hierarchyeval-0.2.2.dist-info/AUTHORS.rst
cellmaps_hierarchyeval-0.2.2.dist-info/LICENSE
cellmaps_hierarchyeval-0.2.2.dist-info/METADATA
cellmaps_hierarchyeval-0.2.2.dist-info/WHEEL
cellmaps_hierarchyeval-0.2.2.dist-info/top_level.txt
cellmaps_hierarchyeval-0.2.2.dist-info/RECORD
