Metadata-Version: 2.1
Name: cellmaps_hierarchyeval
Version: 0.2.2
Summary: A tool to evaluate hierarchies with known resources
Home-page: https://github.com/idekerlab/cellmaps_hierarchyeval
Author: Cell Maps team
Author-email: tools@cm4ai.org
License: MIT license
Keywords: cellmaps_hierarchyeval
Classifier: Development Status :: 2 - Pre-Alpha
Classifier: Intended Audience :: Developers
Classifier: License :: OSI Approved :: MIT License
Classifier: Natural Language :: English
Classifier: Programming Language :: Python :: 3.8
Classifier: Programming Language :: Python :: 3.9
Classifier: Programming Language :: Python :: 3.10
Classifier: Programming Language :: Python :: 3.11
License-File: LICENSE
License-File: AUTHORS.rst
Requires-Dist: cellmaps-utils <1.0.0,>=0.4.0
Requires-Dist: statsmodels <0.15,>=0.14.1
Requires-Dist: scipy <2.0.0,>=1.10.0
Requires-Dist: tqdm <5.0.0,>=4.66.6
Requires-Dist: numpy <2.0.0,>=1.24.4
Requires-Dist: ndex2 <4.0.0,>=3.6.0
Requires-Dist: requests <3.0.0,>=2.31.0
